README.md
setup.py
vuespa/__init__.py
vuespa.egg-info/PKG-INFO
vuespa.egg-info/SOURCES.txt
vuespa.egg-info/dependency_links.txt
vuespa.egg-info/requires.txt
vuespa.egg-info/top_level.txt