Metadata-Version: 2.1
Name: vuespa
Version: 0.3.6
Summary: Helper library for Python+Vue Single Page Applications
Home-page: https://github.com/wwoods/python-vuespa
Author: Walt Woods
Author-email: woodswalben@gmail.com
License: UNKNOWN
Platform: UNKNOWN
Classifier: Programming Language :: Python :: 3
Classifier: License :: OSI Approved :: MIT License
Classifier: Operating System :: OS Independent
